civitdl_z/__init__.py
civitdl_z/__main__.py
civitdl_z/batch_download.py
civitdl_z/command_line.py
civitdl_z/exceptions.py
civitdl_z/filters.py
civitdl_z/get_model.py
civitdl_z/utils.py
civitdl_z-1.2.4.dist-info/License
civitdl_z-1.2.4.dist-info/METADATA
civitdl_z-1.2.4.dist-info/WHEEL
civitdl_z-1.2.4.dist-info/entry_points.txt
civitdl_z-1.2.4.dist-info/top_level.txt
civitdl_z-1.2.4.dist-info/RECORD
