Metadata-Version: 2.1
Name: civitdl-z
Version: 1.2.4
Summary: Package for batch downloading models from civitai.com
Author: Owen Truong
License: MIT License
Project-URL: Repository, https://github.com/OwenTruong/civitdl
Project-URL: Bug Tracker, https://github.com/OwenTruong/civitdl/issues
Keywords: civitai,batch download
Classifier: Programming Language :: Python :: 3
Classifier: License :: OSI Approved :: MIT License
Classifier: Operating System :: OS Independent
Requires-Python: >=3.6
License-File: License
Requires-Dist: requests
Requires-Dist: build
Requires-Dist: termcolor
Requires-Dist: tqdm
